mlc_tools/__init__.py
mlc_tools/main.py
mlc_tools/mlc_tools.py
mlc_tools/version.py
mlc_tools/base/__init__.py
mlc_tools/base/circular_reference.py
mlc_tools/base/data_parser.py
mlc_tools/base/generator.py
mlc_tools/base/generator_data_storage_base.py
mlc_tools/base/generator_operator_equals.py
mlc_tools/base/generator_unit_tests_interface.py
mlc_tools/base/generator_visitor.py
mlc_tools/base/language.py
mlc_tools/base/linker.py
mlc_tools/base/model.py
mlc_tools/base/parser.py
mlc_tools/base/save_plugin_base.py
mlc_tools/base/serializer_base.py
mlc_tools/base/translator_base.py
mlc_tools/base/validator.py
mlc_tools/base/writer_base.py
mlc_tools/console/__init__.py
mlc_tools/console/arguments.py
mlc_tools/console/config.py
mlc_tools/console/console.py
mlc_tools/console/files.py
mlc_tools/core/__init__.py
mlc_tools/core/class_.py
mlc_tools/core/function.py
mlc_tools/core/modifiers.py
mlc_tools/core/object.py
mlc_tools/module_cpp/__init__.py
mlc_tools/module_cpp/cpp_extension.py
mlc_tools/module_cpp/generator.py
mlc_tools/module_cpp/generator_data_storage.py
mlc_tools/module_cpp/generator_observer.py
mlc_tools/module_cpp/generator_operator_equals.py
mlc_tools/module_cpp/generator_predefined_files.py
mlc_tools/module_cpp/generator_ref_counter.py
mlc_tools/module_cpp/protocols.py
mlc_tools/module_cpp/regex.py
mlc_tools/module_cpp/registrar.py
mlc_tools/module_cpp/save_plugin.py
mlc_tools/module_cpp/serializer.py
mlc_tools/module_cpp/translator.py
mlc_tools/module_cpp/writer.py
mlc_tools/module_js/__init__.py
mlc_tools/module_js/constants.py
mlc_tools/module_js/generator.py
mlc_tools/module_js/generator_config.py
mlc_tools/module_js/generator_data_storage.py
mlc_tools/module_js/generator_factory.py
mlc_tools/module_js/generator_functions.py
mlc_tools/module_js/generator_observer.py
mlc_tools/module_js/generator_operator_value_of.py
mlc_tools/module_js/generator_predefined_files.py
mlc_tools/module_js/protocols.py
mlc_tools/module_js/regex.py
mlc_tools-0.4.1113.dist-info/LICENSE
mlc_tools-0.4.1113.dist-info/METADATA
mlc_tools-0.4.1113.dist-info/WHEEL
mlc_tools-0.4.1113.dist-info/entry_points.txt
mlc_tools-0.4.1113.dist-info/top_level.txt
mlc_tools-0.4.1113.dist-info/RECORD
