Metadata-Version: 2.1
Name: mlc-tools
Version: 0.4.1113
Summary: A tool to generate and translate C++ code to other languages from one code-base.
Home-page: https://github.com/mlc-tools/mlc-tools
Author: Vladimir Tolmachev
Author-email: tolm_vl@hotmail.com
Classifier: Programming Language :: Python :: 3
Classifier: License :: OSI Approved :: MIT License
Classifier: Operating System :: OS Independent
Requires-Python: >=3.6
License-File: LICENSE
Requires-Dist: PyYaml
